[
  {
    "id": 20260616,
    "yil": 1448,
    "ay": 1,
    "tarih": "16.06.2026",
    "yer": "Türkiye, Almanya/Germany",
    "durum": "seen",
    "resim_sayisi": 2,
    "video_sayisi": 0
  }
,
  {
    "id": 20260517,
    "yil": 1447,
    "ay": 12,
    "tarih": "17.05.2026",
    "yer": "Gebze/TR",
    "durum": "seen",
    "resim_sayisi": 2,
    "video_sayisi": 0
  }
,
  {
    "id": 20260418,
    "yil": 1447,
    "ay": 11,
    "tarih": "17.04.2026",
    "yer": "",
    "durum": "unseen",
    "resim_sayisi": 2,
    "video_sayisi": 0
  }
]
